omuplugin_onecomme/__init__.py
omuplugin_onecomme/onecomme.py
omuplugin_onecomme/plugin.py
omuplugin_onecomme/types.py
omuplugin_onecomme/version.py
omuplugin_onecomme-0.7.14.dist-info/METADATA
omuplugin_onecomme-0.7.14.dist-info/WHEEL
omuplugin_onecomme-0.7.14.dist-info/entry_points.txt
omuplugin_onecomme-0.7.14.dist-info/RECORD
