Metadata-Version: 2.3
Name: omuplugin_onecomme
Version: 0.7.14
Summary: わんコメとつなげるためのOMUAPPSプラグイン
Author-email: am230 <111672334+am230@users.noreply.github.com>
Requires-Python: >=3.12
Requires-Dist: loguru>=0.7.2
Requires-Dist: omu-chat>=0.7.14
Requires-Dist: psutil>=6.0.0
